peerjs/api.py
peerjs/baseconnection.py
peerjs/dataconnection.py
peerjs/enums.py
peerjs/negotiator.py
peerjs/peer.py
peerjs/peerroom.py
peerjs/servermessage.py
peerjs/socket.py
peerjs/util.py
peerjs/ext/http_proxy.py
peerjs-1.5.1.dist-info/METADATA
peerjs-1.5.1.dist-info/WHEEL
peerjs-1.5.1.dist-info/top_level.txt
peerjs-1.5.1.dist-info/RECORD
