Metadata-Version: 2.1
Name: peerjs
Version: 1.5.1
Summary: Python port of PeerJS client library.
Home-page: https://github.com/ambianic/peerjs-python
Author: Ivelin Ivanov
Author-email: ivelin.ivanov@ambianic.ai
License: Apache Software License 2.0
Platform: UNKNOWN
Classifier: Development Status :: 4 - Beta
Classifier: Programming Language :: Python :: 3
Classifier: License :: OSI Approved :: Apache Software License
Classifier: Operating System :: OS Independent
Classifier: Topic :: Communications
Classifier: Topic :: Software Development :: Embedded Systems
Classifier: Intended Audience :: Developers
Requires-Python: >=3.7
Requires-Dist: av (~=8.0.0)
Requires-Dist: aiortc (>=0.9)
Requires-Dist: websockets (>=8.1)
Requires-Dist: aiohttp (>=3.6)
Requires-Dist: pyee (>=6.0)
Requires-Dist: dataclasses-json (>=0.3)
Requires-Dist: loguru (>=0.5)
Requires-Dist: pyyaml (>=5.3.1)
